bvk/__init__.py
bvk/items.py
bvk/settings.py
bvk/spiders/__init__.py
bvk/spiders/water_consumption.py
python_bvk-0.4.1.dist-info/WHEEL
python_bvk-0.4.1.dist-info/METADATA
python_bvk-0.4.1.dist-info/RECORD
