Metadata-Version: 2.4
Name: python-bvk
Version: 0.4.1
Summary: Python library for tracking water consumption from BVK (Brnenske vodarny a kanalizace, bvk.cz)
Keywords: scrapy,water consumption,bvk
Author: Dan Keder
Author-email: Dan Keder <dan.keder@protonmail.com>
License-Expression: Apache-2.0
Classifier: Programming Language :: Python :: 3
Classifier: Operating System :: OS Independent
Requires-Dist: scrapy<=2.13.0
Requires-Dist: python-dateutil
Requires-Python: >=3.9
Project-URL: Homepage, https://github.com/dankeder/python-bvk
